rodeo/__init__.py
rodeo/interrogate.py
rodeo/solve.py
rodeo/utils.py
rodeo/inference/__init__.py
rodeo/inference/basic.py
rodeo/inference/dalton.py
rodeo/inference/fenrir.py
rodeo/inference/magi.py
rodeo/inference/pseudo_marginal.py
rodeo/kalmantv/__init__.py
rodeo/kalmantv/square_root.py
rodeo/kalmantv/standard.py
rodeo/prior/__init__.py
rodeo/prior/ibm.py
rodeo/prior/indep_init.py
rodeo-1.1.3.dist-info/licenses/LICENSE.txt
rodeo-1.1.3.dist-info/METADATA
rodeo-1.1.3.dist-info/WHEEL
rodeo-1.1.3.dist-info/top_level.txt
rodeo-1.1.3.dist-info/RECORD
