Metadata-Version: 2.4
Name: rodeo
Version: 1.1.3
Summary: Probabilistic Methods of Parameter Inference for ODEs
Author-email: Mohan Wu <mhwu@uwaterloo.ca>, Martin Lysy <mlysy@uwaterloo.ca>
Maintainer-email: Martin Lysy <mlysy@uwaterloo.ca>
License-Expression: MIT
Project-URL: repository, https://github.com/mlysy/rodeo
Project-URL: documentation, https://rodeo.readthedocs.io/
Keywords: jax,parameter-inference,differential-equations,rodeo,probabilistic-solver
Classifier: Development Status :: 3 - Alpha
Classifier: Intended Audience :: Developers
Classifier: Intended Audience :: Information Technology
Classifier: Intended Audience :: Science/Research
Classifier: Natural Language :: English
Classifier: Programming Language :: Python :: 3
Classifier: Topic :: Scientific/Engineering
Classifier: Topic :: Scientific/Engineering :: Artificial Intelligence
Classifier: Topic :: Scientific/Engineering :: Mathematics
Requires-Python: >=3.9
License-File: LICENSE.txt
Requires-Dist: jaxlib
Requires-Dist: jax
Requires-Dist: blackjax<=1.2.3; python_version < "3.10"
Requires-Dist: blackjax; python_version >= "3.10"
Provides-Extra: docs
Requires-Dist: numpy; extra == "docs"
Requires-Dist: scipy; extra == "docs"
Requires-Dist: jaxopt; extra == "docs"
Requires-Dist: matplotlib; extra == "docs"
Requires-Dist: seaborn; extra == "docs"
Requires-Dist: myst_nb; extra == "docs"
Requires-Dist: sphinx_rtd_theme; extra == "docs"
Requires-Dist: jupytext; extra == "docs"
Dynamic: license-file
